kspdf/__init__.py
kspdf/pdf2img.py
kspdf/pdf2text.py
kspdf-0.0.1.dist-info/LICENCE
kspdf-0.0.1.dist-info/METADATA
kspdf-0.0.1.dist-info/WHEEL
kspdf-0.0.1.dist-info/top_level.txt
kspdf-0.0.1.dist-info/RECORD
