Metadata-Version: 2.1
Name: kspdf
Version: 0.0.1
License-File: LICENCE
